setup.py
client/__init__.py
client/__main__.py
client/client.py
client/client_gui.py
client/client_db/__init__.py
client/client_db/client_data_services.py
client/client_db/data/__init__.py
client/client_db/data/session_factory.py
client/client_db/data/sqlalchemybase.py
client/client_db/db/__init__.py
client/client_db/db/db_folder.py
client/client_db/models/__init__.py
client/client_db/models/client_models.py
client/common/__init__.py
client/common/arg_parser.py
client/common/decos.py
client/common/descriptors.py
client/common/host_ping.py
client/common/metaclasses.py
client/common/utils.py
client/jim/__init__.py
client/jim/core.py
client/jim/errors.py
client/log/__init__.py
client/log/client_log_config.py
client/log/server_log_config.py
client/ui/__init__.py
client/ui/add_contact_UIs.py
client/ui/client_UIs.py
client/ui/client_gui_settings.py
client/ui/connect_user_UIs.py
client/ui/del_contact_UIs.py
client/unit_tests/__init__.py
client/unit_tests/test_client.py
client/unit_tests/test_server.py
client/unit_tests/test_utils.py
pyside2_mess_client.egg-info/PKG-INFO
pyside2_mess_client.egg-info/SOURCES.txt
pyside2_mess_client.egg-info/dependency_links.txt
pyside2_mess_client.egg-info/requires.txt
pyside2_mess_client.egg-info/top_level.txt