Metadata-Version: 1.0
Name: pyside2-mess-client
Version: 0.1
Summary: PySide2 messenger - Client package
Home-page: UNKNOWN
Author: MaximR
Author-email: support@geekbrains.ru
License: UNKNOWN
Platform: UNKNOWN
